Apside/__init__.py
Apside/acceleration.py
Apside/backwardintegrator.py
Apside/coordinates.py
Apside/energy.py
Apside/fetchgaia.py
Apside/leapfrog.py
Apside/velocity.py
apside-1.0.dist-info/METADATA
apside-1.0.dist-info/WHEEL
apside-1.0.dist-info/entry_points.txt
apside-1.0.dist-info/top_level.txt
apside-1.0.dist-info/RECORD
