Metadata-Version: 2.4
Name: Apside
Version: 1.0
Author: Venkata Pendyala
Author-email: venkatasiddharthpendyala@gmail.com
Requires-Dist: numpy
Requires-Dist: numba
Requires-Dist: astroquery
Dynamic: author
Dynamic: author-email
Dynamic: description
Dynamic: description-content-type
Dynamic: requires-dist
